app/__init__.py
app/cli.py
app/defaults.py
app/elastic_api.py
app/exceptions.py
app/helpers.py
app/logtools.py
app/main.py
app/redacters.py
app/tracking.py
app/version.py
app/waiters.py
elasticsearch_pii_redacter-1.11.0.dist-info/METADATA
elasticsearch_pii_redacter-1.11.0.dist-info/WHEEL
elasticsearch_pii_redacter-1.11.0.dist-info/entry_points.txt
elasticsearch_pii_redacter-1.11.0.dist-info/RECORD
